shivonai/__init__.py
shivonai/core/__init__.py
shivonai/core/mcp_client.py
shivonai/lyra/__init__.py
shivonai/lyra/agno_tools.py
shivonai/lyra/crew_tools.py
shivonai/lyra/langchain_tools.py
shivonai/lyra/llamaindex_tools.py
shivonai/utils/__init__.py
shivonai/utils/helpers.py
shivonai-0.1.4.dist-info/licenses/LICENSE
shivonai-0.1.4.dist-info/METADATA
shivonai-0.1.4.dist-info/WHEEL
shivonai-0.1.4.dist-info/top_level.txt
shivonai-0.1.4.dist-info/RECORD
