Metadata-Version: 2.4
Name: shivonai
Version: 0.1.4
Summary: Tools for connecting AI agents with MCP server
Author-email: Shivon AI <contact@shivonai.com>
License: Proprietary
Project-URL: Homepage, https://github.com/shivonai/python_package
Project-URL: Bug Tracker, https://github.com/shivonai/python_package/issues
Classifier: Programming Language :: Python :: 3
Classifier: License :: Other/Proprietary License
Classifier: Operating System :: OS Independent
Requires-Python: >=3.7
License-File: LICENSE
Requires-Dist: requests>=2.25.0
Provides-Extra: langchain
Requires-Dist: langchain>=0.1.0; extra == "langchain"
Provides-Extra: llamaindex
Requires-Dist: llama-index>=0.1.0; extra == "llamaindex"
Provides-Extra: crewai
Requires-Dist: crewai>=0.1.0; extra == "crewai"
Provides-Extra: agno
Requires-Dist: agno>=0.1.0; extra == "agno"
Provides-Extra: all
Requires-Dist: langchain>=0.1.0; extra == "all"
Requires-Dist: llama-index>=0.1.0; extra == "all"
Requires-Dist: crewai>=0.1.0; extra == "all"
Requires-Dist: agno>=0.1.0; extra == "all"
Dynamic: license-file
